dbt/adapters/gizmosql/__init__.py
dbt/adapters/gizmosql/__version__.py
dbt/adapters/gizmosql/column.py
dbt/adapters/gizmosql/connections.py
dbt/adapters/gizmosql/impl.py
dbt/adapters/gizmosql/relation.py
dbt/include/gizmosql/__init__.py
dbt/include/gizmosql/dbt_project.yml
dbt/include/gizmosql/profile_template.yml
dbt/include/gizmosql/macros/adapters.sql
dbt/include/gizmosql/macros/catalog.sql
dbt_gizmosql-1.11.2.dist-info/licenses/LICENSE
dbt_gizmosql-1.11.2.dist-info/METADATA
dbt_gizmosql-1.11.2.dist-info/WHEEL
dbt_gizmosql-1.11.2.dist-info/top_level.txt
dbt_gizmosql-1.11.2.dist-info/RECORD
