Metadata-Version: 2.4
Name: dbt-gizmosql
Version: 1.11.2
Summary: The GizmoSQL adapter plugin for dbt
Author-email: Philip Moore <philip@gizmodata.com>
License-Expression: Apache-2.0
Project-URL: Homepage, https://github.com/gizmodata/dbt-gizmosql
Keywords: dbt,gizmosql,flightsql,duckdb,adbc,gizmodata
Classifier: Programming Language :: Python
Classifier: Programming Language :: Python :: 3
License-File: LICENSE
Requires-Dist: dbt-core~=1.11.2
Requires-Dist: dbt-common~=1.37.2
Requires-Dist: dbt-adapters~=1.22.4
Requires-Dist: adbc-driver-flightsql~=1.10.0
Requires-Dist: pyarrow==22.0.*
Provides-Extra: dev
Requires-Dist: pip-tools; extra == "dev"
Requires-Dist: pytest; extra == "dev"
Requires-Dist: dbt-tests-adapter==1.19.*; extra == "dev"
Requires-Dist: black==24.2.0; extra == "dev"
Requires-Dist: bumpversion; extra == "dev"
Requires-Dist: flake8; extra == "dev"
Requires-Dist: flaky; extra == "dev"
Requires-Dist: freezegun==1.4.0; extra == "dev"
Requires-Dist: ipdb; extra == "dev"
Requires-Dist: mypy==1.8.0; extra == "dev"
Requires-Dist: pre-commit; extra == "dev"
Requires-Dist: pytest-dotenv; extra == "dev"
Requires-Dist: pytest-csv; extra == "dev"
Requires-Dist: pytest-xdist; extra == "dev"
Requires-Dist: pytz; extra == "dev"
Requires-Dist: tox>=3.13; extra == "dev"
Requires-Dist: twine; extra == "dev"
Requires-Dist: wheel; extra == "dev"
Requires-Dist: docker; extra == "dev"
Dynamic: license-file
